autofe/__init__.py
autofe/autofe.py
auto_feature_engineering-0.0.2.dist-info/LICENSE
auto_feature_engineering-0.0.2.dist-info/METADATA
auto_feature_engineering-0.0.2.dist-info/WHEEL
auto_feature_engineering-0.0.2.dist-info/top_level.txt
auto_feature_engineering-0.0.2.dist-info/RECORD
