Metadata-Version: 2.1
Name: auto-feature-engineering
Version: 0.0.2
Summary: A package for automatically generating features
Home-page: https://github.com/LeylaWong/autoFE
Author: Xinlin Wang
Author-email: xinlin.wang.stats@gmail.com
Classifier: Programming Language :: Python :: 3
Classifier: License :: OSI Approved :: MIT License
Classifier: Operating System :: OS Independent
Requires-Python: >=3.8
License-File: LICENSE
Requires-Dist: pandas (==1.3.5)
Requires-Dist: numpy (==1.20.0)
Requires-Dist: lightgbm (==3.3.2)
Requires-Dist: scikit-learn (==1.0.1)
Requires-Dist: multiprocess (==0.70.14)
